{
  "testResults": [
    {
      "mbtiResult": "ESTJ",
      "timestamp": "2024-11-26T06:57:32.033Z",
      "id": 1
    },
    {
      "mbtiResult": "ESTJ",
      "timestamp": "2024-11-26T06:57:37.248Z",
      "id": 2
    },
    {
      "mbtiResult": "ESTJ",
      "timestamp": "2024-11-26T06:57:43.284Z",
      "id": 3
    },
    {
      "mbtiResult": "ESFJ",
      "timestamp": "2024-11-26T06:57:53.364Z",
      "id": 4
    },
    {
      "mbtiResult": "INTP",
      "timestamp": "2024-11-26T06:58:08.726Z",
      "id": 5
    },
    {
      "mbtiResult": "ESTJ",
      "timestamp": "2024-11-26T15:40:28.042Z",
      "id": 6
    },
    {
      "mbtiResult": "ESTJ",
      "timestamp": "2024-11-26T15:54:35.873Z",
      "id": 7
    },
    {
      "mbtiResult": "ESTJ",
      "timestamp": "2024-11-26T16:14:12.312Z",
      "id": 8
    },
    {
      "mbtiResult": "ESTJ",
      "timestamp": "2024-11-27T02:05:37.540Z",
      "id": 9
    },
    {
      "mbtiResult": "ESTJ",
      "timestamp": "2024-11-27T02:31:15.275Z",
      "id": 10
    }
  ]
}